malpediaclient
