Metadata-Version: 2.1
Name: malpediaclient
Version: 0.3.2
Summary: Malpedia REST API Client.
Home-page: https://malpedia.caad.fkie.fraunhofer.de
Author: Steffen Enders
Author-email: steffen.enders@tu-dortmund.de
License:                                  Apache License
Classifier: Development Status :: 5 - Production/Stable
Classifier: Intended Audience :: Information Technology
Classifier: Intended Audience :: Science/Research
Classifier: License :: OSI Approved :: MIT License
Classifier: Programming Language :: Python :: 3
Classifier: Programming Language :: Python :: 3.6
Classifier: Programming Language :: Python :: 3.7
Classifier: Programming Language :: Python :: 3.8
Classifier: Programming Language :: Python :: 3.9
Classifier: Programming Language :: Python :: 3.10
Classifier: Programming Language :: Python :: 3.11
Classifier: Programming Language :: Python :: 3.12
Classifier: Topic :: Security
Requires-Python: >=3.6
License-File: LICENSE
